LICENSE
MANIFEST.in
README.md
setup.py
acme/__init__.py
acme/_metadata.py
acme/core.py
acme/core_test.py
acme/environment_loop.py
acme/environment_loop_test.py
acme/specs.py
acme/types.py
acme/adders/__init__.py
acme/adders/base.py
acme/adders/wrappers.py
acme/adders/reverb/__init__.py
acme/adders/reverb/base.py
acme/adders/reverb/episode.py
acme/adders/reverb/episode_test.py
acme/adders/reverb/sequence.py
acme/adders/reverb/sequence_test.py
acme/adders/reverb/test_cases.py
acme/adders/reverb/test_utils.py
acme/adders/reverb/transition.py
acme/adders/reverb/transition_test.py
acme/adders/reverb/utils.py
acme/agents/__init__.py
acme/agents/agent.py
acme/agents/replay.py
acme/agents/jax/__init__.py
acme/agents/jax/actor_core.py
acme/agents/jax/actors.py
acme/agents/jax/actors_test.py
acme/agents/jax/builders.py
acme/agents/jax/normalization.py
acme/agents/jax/ail/__init__.py
acme/agents/jax/ail/agent_test.py
acme/agents/jax/ail/agents.py
acme/agents/jax/ail/builder.py
acme/agents/jax/ail/builder_test.py
acme/agents/jax/ail/config.py
acme/agents/jax/ail/dac_agents.py
acme/agents/jax/ail/gail_agents.py
acme/agents/jax/ail/learning.py
acme/agents/jax/ail/learning_test.py
acme/agents/jax/ail/losses.py
acme/agents/jax/ail/losses_test.py
acme/agents/jax/ail/networks.py
acme/agents/jax/ail/rewards.py
acme/agents/jax/bc/__init__.py
acme/agents/jax/bc/agent_test.py
acme/agents/jax/bc/learning.py
acme/agents/jax/bc/losses.py
acme/agents/jax/bc/pretraining.py
acme/agents/jax/d4pg/__init__.py
acme/agents/jax/d4pg/agent_test.py
acme/agents/jax/d4pg/agents.py
acme/agents/jax/d4pg/builder.py
acme/agents/jax/d4pg/config.py
acme/agents/jax/d4pg/learning.py
acme/agents/jax/d4pg/networks.py
acme/agents/jax/dqn/__init__.py
acme/agents/jax/dqn/actor.py
acme/agents/jax/dqn/agent.py
acme/agents/jax/dqn/agent_test.py
acme/agents/jax/dqn/builder.py
acme/agents/jax/dqn/config.py
acme/agents/jax/dqn/learning.py
acme/agents/jax/dqn/learning_lib.py
acme/agents/jax/dqn/losses.py
dm_acme.egg-info/PKG-INFO
dm_acme.egg-info/SOURCES.txt
dm_acme.egg-info/dependency_links.txt
dm_acme.egg-info/requires.txt
dm_acme.egg-info/top_level.txt