Metadata-Version: 2.1
Name: dm-acme
Version: 0.4.0
Summary: A Python library for Reinforcement Learning.
Author: DeepMind
License: Apache License, Version 2.0
Keywords: reinforcement-learning python machine learning
Platform: UNKNOWN
Classifier: Development Status :: 3 - Alpha
Classifier: Environment :: Console
Classifier: Intended Audience :: Science/Research
Classifier: License :: OSI Approved :: Apache Software License
Classifier: Operating System :: POSIX :: Linux
Classifier: Programming Language :: Python :: 3
Classifier: Programming Language :: Python :: 3.7
Classifier: Programming Language :: Python :: 3.8
Classifier: Programming Language :: Python :: 3.9
Classifier: Topic :: Scientific/Engineering :: Artificial Intelligence
Provides-Extra: jax
Provides-Extra: tf
Provides-Extra: testing
Provides-Extra: envs
License-File: LICENSE
